sticker_generator/__init__.py
sticker_generator/cli.py
sticker_generator/core.py
sticker_generator/formats.py
sticker_generator/image_processing.py
sticker_generator/sheet.py
sticker_generator/styles.py
sticker_generator-0.5.2.dist-info/METADATA
sticker_generator-0.5.2.dist-info/WHEEL
sticker_generator-0.5.2.dist-info/entry_points.txt
sticker_generator-0.5.2.dist-info/licenses/LICENSE
sticker_generator-0.5.2.dist-info/RECORD
