Metadata-Version: 2.4
Name: sticker-generator
Version: 0.5.2
Summary: Generate stickers with transparent backgrounds using Gemini AI
Project-URL: Homepage, https://github.com/eyenpi/sticker-generator
Project-URL: Repository, https://github.com/eyenpi/sticker-generator
Project-URL: Issues, https://github.com/eyenpi/sticker-generator/issues
Author: Eyenpi
License-Expression: MIT
License-File: LICENSE
Keywords: ai,gemini,image-generation,sticker
Classifier: License :: OSI Approved :: MIT License
Classifier: Operating System :: OS Independent
Classifier: Programming Language :: Python :: 3
Classifier: Programming Language :: Python :: 3.10
Classifier: Programming Language :: Python :: 3.11
Classifier: Programming Language :: Python :: 3.12
Classifier: Programming Language :: Python :: 3.13
Classifier: Topic :: Multimedia :: Graphics
Requires-Python: >=3.10
Requires-Dist: google-genai>=1.0.0
Requires-Dist: numpy>=1.24.0
Requires-Dist: pillow>=10.0.0
Requires-Dist: scipy>=1.10.0
Provides-Extra: dev
Requires-Dist: mypy>=1.0.0; extra == 'dev'
Requires-Dist: pytest-cov>=4.0.0; extra == 'dev'
Requires-Dist: pytest>=7.0.0; extra == 'dev'
Requires-Dist: ruff>=0.1.0; extra == 'dev'
